seali/__init__.py
seali/config.py
seali/main.py
seali/py.typed
seali/requests/__init__.py
seali/requests/data.py
seali/requests/project.py
seali/typer/__init__.py
seali/typer/data.py
seali/typer/project.py
seali-0.1.0.dist-info/LICENSE
seali-0.1.0.dist-info/METADATA
seali-0.1.0.dist-info/WHEEL
seali-0.1.0.dist-info/entry_points.txt
seali-0.1.0.dist-info/top_level.txt
seali-0.1.0.dist-info/RECORD
